rela/__init__.py
rela/_rela.py
rela/_test.py
rela/_utils.py
rela-0.1.0.dist-info/LICENSE.txt
rela-0.1.0.dist-info/METADATA
rela-0.1.0.dist-info/WHEEL
rela-0.1.0.dist-info/top_level.txt
rela-0.1.0.dist-info/RECORD
