Metadata-Version: 2.1
Name: rela
Version: 0.1.0
Summary: rela.tive imports from `__main__` and some test helpers
Author-email: "Roger D. Serwy" <roger.serwy@gmail.com>
License: NCSA
Project-URL: Homepage, https://github.com/serwy/rela
Classifier: Development Status :: 3 - Alpha
Classifier: License :: OSI Approved :: University of Illinois/NCSA Open Source License
Requires-Python: >=3.6
License-File: LICENSE.txt
